simple_features/__init__.py
simple_features-1.0.4.dist-info/WHEEL
simple_features-1.0.4.dist-info/METADATA
simple_features-1.0.4.dist-info/RECORD
