Metadata-Version: 2.1
Name: simple-features
Version: 1.0.4
Summary: Just some simple additions to your python experience like most 3-4 bit colors and making useful commands like time.sleep(null) and os.system('clear') more user friendly.
Author: Stefan Dikov
Author-email: stefan.v.dikov@gmail.com
Requires-Python: >=3.10,<4.0
Classifier: Programming Language :: Python :: 3
Classifier: Programming Language :: Python :: 3.10
